{
  "appIsExample": false,
  "appLayout": {
    "type": "FLUID"
  },
  "applicationDetail": {
    "appPositioning": {
      "type": "FIXED"
    },
    "navigationSetting": {
      "colorStyle": "light",
      "itemStyle": "text",
      "logoAssetId": "",
      "logoConfiguration": "logoAndApplicationTitle",
      "navStyle": "sidebar",
      "orientation": "side",
      "position": "static",
      "showNavbar": true,
      "showSignIn": true
    }
  },
  "applicationVersion": 2,
  "collapseInvisibleWidgets": true,
  "color": "#F5D1D1",
  "evaluationVersion": 2,
  "icon": "bird",
  "pages": [
    {
      "id": "Page1",
      "isDefault": false
    },
    {
      "id": "Page2",
      "isDefault": false
    },
    {
      "id": "Open Transaction Groups",
      "isDefault": true
    }
  ],
  "unpublishedAppLayout": {
    "type": "FLUID"
  },
  "unpublishedApplicationDetail": {
    "appPositioning": {
      "type": "FIXED"
    },
    "navigationSetting": {
      "colorStyle": "light",
      "itemStyle": "text",
      "logoAssetId": "",
      "logoConfiguration": "logoAndApplicationTitle",
      "navStyle": "sidebar",
      "orientation": "side",
      "position": "static",
      "showNavbar": true,
      "showSignIn": true
    }
  }
}